RemarkableSync.py
remarkablesync-1.0.8.dist-info/licenses/LICENSE
src/__init__.py
src/__version__.py
src/converter.py
src/hybrid_converter.py
src/template_renderer.py
src/backup/__init__.py
src/backup/backup_manager.py
src/backup/connection.py
src/backup/metadata.py
src/commands/__init__.py
src/commands/backup_command.py
src/commands/convert_command.py
src/commands/sync_command.py
src/converters/__init__.py
src/converters/base_converter.py
src/converters/v4_converter.py
src/converters/v5_converter.py
src/converters/v6_converter.py
src/utils/__init__.py
src/utils/logging.py
remarkablesync-1.0.8.dist-info/METADATA
remarkablesync-1.0.8.dist-info/WHEEL
remarkablesync-1.0.8.dist-info/entry_points.txt
remarkablesync-1.0.8.dist-info/top_level.txt
remarkablesync-1.0.8.dist-info/RECORD
