Metadata-Version: 2.4
Name: remarkablesync
Version: 1.0.8
Summary: Backup and convert reMarkable tablet notebooks to PDF
Home-page: https://github.com/JeffSteinbok/RemarkableSync
Author: Jeff Steinbok
Author-email: 
License: MIT
Keywords: remarkable tablet backup pdf converter
Classifier: Development Status :: 4 - Beta
Classifier: Intended Audience :: End Users/Desktop
Classifier: License :: OSI Approved :: MIT License
Classifier: Operating System :: OS Independent
Classifier: Programming Language :: Python :: 3
Classifier: Programming Language :: Python :: 3.11
Classifier: Programming Language :: Python :: 3.12
Classifier: Programming Language :: Python :: 3.13
Classifier: Topic :: Utilities
Requires-Python: >=3.11
License-File: LICENSE
Requires-Dist: paramiko>=3.0.0
Requires-Dist: scp>=0.14.5
Requires-Dist: requests>=2.31.0
Requires-Dist: tqdm>=4.66.0
Requires-Dist: python-dateutil>=2.8.2
Requires-Dist: click>=8.1.0
Requires-Dist: pathlib2>=2.3.7
Requires-Dist: cryptography>=41.0.0
Requires-Dist: PyPDF2>=3.0.0
Requires-Dist: svglib>=1.5.0
Requires-Dist: reportlab>=4.0.0
Requires-Dist: keyring>=24.0.0
Requires-Dist: rmc>=0.3.0
Dynamic: author
Dynamic: classifier
Dynamic: description
Dynamic: description-content-type
Dynamic: home-page
Dynamic: keywords
Dynamic: license
Dynamic: license-file
Dynamic: requires-dist
Dynamic: requires-python
Dynamic: summary
